LICENSE
MANIFEST.in
README.md
pyproject.toml
setup.cfg
setup.py
hfst_optimized_lookup/__VERSION__
hfst_optimized_lookup/__init__.py
hfst_optimized_lookup/_hfst_optimized_lookup.cpp
hfst_optimized_lookup/_hfst_optimized_lookup.h
hfst_optimized_lookup/_hfst_optimized_lookup.pyi
hfst_optimized_lookup/_hfst_optimized_lookup.pyx
hfst_optimized_lookup/_types.py
hfst_optimized_lookup/hfst-optimized-lookup.cc
hfst_optimized_lookup/hfst-optimized-lookup.h
hfst_optimized_lookup/py.typed
hfst_optimized_lookup.egg-info/PKG-INFO
hfst_optimized_lookup.egg-info/SOURCES.txt
hfst_optimized_lookup.egg-info/dependency_links.txt
hfst_optimized_lookup.egg-info/top_level.txt