Metadata-Version: 2.4
Name: hfst-optimized-lookup
Version: 0.0.14
Summary: A pip-installable library version of hfst-optimized-lookup from https://hfst.github.io/
Home-page: https://github.com/UAlbertaALTLab/hfst-optimized-lookup
Author: Andrew Neitsch
Author-email: 178162+andrewdotn@users.noreply.github.com
License: Apache-2.0
Classifier: License :: OSI Approved :: Apache Software License
Classifier: Topic :: Text Processing :: Linguistic
License-File: LICENSE
Dynamic: author
Dynamic: author-email
Dynamic: classifier
Dynamic: description
Dynamic: description-content-type
Dynamic: home-page
Dynamic: license
Dynamic: license-file
Dynamic: summary
